pandasgui/__init__.py
pandasgui/dataframe_viewer.py
pandasgui/dialogs.py
pandasgui/functions.py
pandasgui/gui.py
pandasgui/image_viewer.py
pandasgui/nonblocking.py
pandasgui/scratch.py
pandasgui/speed_test_scratch.py
pandasgui-0.0.4.dist-info/LICENSE.txt
pandasgui-0.0.4.dist-info/METADATA
pandasgui-0.0.4.dist-info/WHEEL
pandasgui-0.0.4.dist-info/top_level.txt
pandasgui-0.0.4.dist-info/RECORD
