Metadata-Version: 2.1
Name: pandasgui
Version: 0.0.4
Summary: GUI for Pandas DataFrames
Home-page: https://github.com/adamerose/pandasgui
Author: Adam Rose
Author-email: adamerose@hotmail.com
License: UNKNOWN
Platform: UNKNOWN
Requires-Dist: pandas
Requires-Dist: PyQt5
Requires-Dist: multiprocess
